{
  "playbooks": [
    {
      "id": "plugin-load-failure-triage",
      "title": "Plugin load failure triage",
      "summary": "The plugin failed before it became usable. Confirm deployment, manifest identity, and the earliest stack trace before changing unrelated UI code.",
      "match": {
        "signatureAny": [
          "plugin-load-failed",
          "plugin-runtime-exception",
          "module-resolution-failed",
          "manifest-or-version-invalid"
        ]
      },
      "files": [
        "manifest.json",
        "package.json",
        "src/main.*",
        "src/**/*",
        "dist/main.js",
        "dist/manifest.json"
      ],
      "commands": [
        {
          "id": "doctor-with-fix-plan",
          "label": "Generate a doctor fix plan",
          "summary": "Capture missing build/deploy/CLI/CDP prerequisites and write a reviewable fix script next to the doctor report.",
          "safety": "read-only",
          "dryRunFriendly": true,
          "executable": "node",
          "args": [
            "{{toolRoot}}/scripts/obsidian_debug_doctor.mjs",
            "--repo-dir",
            "{{repoDir}}",
            "--plugin-id",
            "{{pluginId}}",
            "--test-vault-plugin-dir",
            "{{testVaultPluginDir}}",
            "--obsidian-command",
            "{{obsidianCommand}}",
            "--output",
            "{{outputDir}}/doctor.json",
            "--fix"
          ]
        }
      ],
      "actions": [
        "Compare the repo manifest, dist manifest, and test vault manifest before changing source code.",
        "Use the earliest stack trace after reload as the root symptom.",
        "Rebuild and redeploy generated artifacts before retrying plugin reload."
      ]
    },
    {
      "id": "app-control-recovery",
      "title": "Obsidian app-control recovery",
      "summary": "CLI or CDP automation could not reach the target Obsidian desktop instance. Fix the app-control surface before trusting plugin diagnostics.",
      "match": {
        "signatureAny": [
          "obsidian-cli-app-unavailable",
          "cdp-target-unreachable"
        ]
      },
      "files": [
        "job-specs/generic-debug-job.template.json",
        "scripts/obsidian_debug_doctor.mjs",
        "scripts/obsidian_mac_restart_cdp.sh"
      ],
      "commands": [
        {
          "id": "probe-cdp-targets",
          "label": "Probe CDP targets",
          "summary": "List exposed CDP targets before retrying CDP automation.",
          "safety": "read-only",
          "dryRunFriendly": true,
          "platform": "auto",
          "executable": "node",
          "args": [
            "--input-type=module",
            "-e",
            "const response = await fetch('http://127.0.0.1:9222/json/list'); console.log(await response.text());"
          ]
        }
      ],
      "actions": [
        "Launch Obsidian desktop and open or focus the target test vault before retrying CLI commands.",
        "If using CDP, restart Obsidian with a debug port and filter by vault title in multi-window setups.",
        "Do not diagnose plugin code until app-control preflight succeeds."
      ]
    },
    {
      "id": "visible-ui-performance-triage",
      "title": "Visible UI performance triage",
      "summary": "Startup or view-open timing crossed a generic budget. Split startup, view construction, render, hydration, and background refresh before changing code.",
      "match": {
        "signatureAny": [
          "slow-startup",
          "slow-view-open"
        ]
      },
      "files": [
        "src/main.*",
        "src/**/*view*",
        "src/**/*startup*",
        "src/**/*settings*",
        "src/**/*state*"
      ],
      "commands": [
        {
          "id": "rerender-report",
          "label": "Rebuild the HTML report",
          "summary": "Produce a portable diagnosis report before comparing warm/cold timing classes.",
          "safety": "read-only",
          "dryRunFriendly": true,
          "executable": "node",
          "args": [
            "{{toolRoot}}/scripts/obsidian_debug_report.mjs",
            "--diagnosis",
            "{{diagnosisPath}}",
            "--output",
            "{{outputDir}}/report.html"
          ]
        }
      ],
      "actions": [
        "Record startup-complete and view-open milestones in the same run.",
        "Render a usable shell before non-critical enrichment work where safe.",
        "Save separate cold-start and warm-start baselines so app variance does not hide regressions."
      ]
    },
    {
      "id": "artifact-capture-gap",
      "title": "Artifact capture recovery",
      "summary": "Screenshot or DOM artifacts are missing, so the run is not trustworthy enough for UI debugging yet.",
      "match": {
        "assertionFailedAny": [
          "screenshot-captured",
          "dom-root-present",
          "screenshot-exists",
          "dom-exists"
        ]
      },
      "files": [
        "scripts/obsidian_plugin_debug_cycle.ps1",
        "scripts/obsidian_plugin_debug_cycle.sh",
        "scripts/obsidian_cdp_capture_ui.mjs"
      ],
      "commands": [
        {
          "id": "retry-cli-screenshot",
          "label": "Retry CLI screenshot capture",
          "summary": "Capture a fresh screenshot directly through the active Obsidian CLI command.",
          "safety": "read-only",
          "dryRunFriendly": true,
          "executable": "{{obsidianCommand}}",
          "args": [
            "dev:screenshot",
            "path={{outputDir}}/screenshot-retry.png"
          ]
        },
        {
          "id": "retry-cli-dom",
          "label": "Retry CLI DOM capture",
          "summary": "Re-query the suspected plugin root selector before trusting downstream UI assertions.",
          "safety": "read-only",
          "dryRunFriendly": true,
          "executable": "{{obsidianCommand}}",
          "args": [
            "dev:dom",
            "selector={{domSelector}}",
            "all"
          ]
        },
        {
          "id": "fallback-cdp-capture",
          "label": "Capture UI through CDP",
          "summary": "Fallback capture path when CLI screenshot or DOM collection still misses the active plugin leaf.",
          "safety": "read-only",
          "dryRunFriendly": true,
          "executable": "node",
          "args": [
            "{{toolRoot}}/scripts/obsidian_cdp_capture_ui.mjs",
            "--host",
            "127.0.0.1",
            "--port",
            "9222",
            "--selector",
            "{{domSelector}}",
            "--html-output",
            "{{outputDir}}/dom-retry.html",
            "--screenshot-output",
            "{{outputDir}}/screenshot-retry.png"
          ]
        }
      ],
      "actions": [
        "Verify the selector targets the plugin pane instead of the previously active leaf.",
        "Use a scenario or CDP post-reload eval to focus/open the plugin view before capture.",
        "Do not trust downstream assertions until both DOM and screenshot capture succeed."
      ]
    }
  ]
}
